CHANGES.rst
LICENSE.txt
MANIFEST.in
README.md
setup.py
datarobot_bp_workshop/__init__.py
datarobot_bp_workshop/_version.py
datarobot_bp_workshop/auto_rate_limiter.py
datarobot_bp_workshop/blueprint_graph.py
datarobot_bp_workshop/dynamic.py
datarobot_bp_workshop/exceptions.py
datarobot_bp_workshop/factories.py
datarobot_bp_workshop/friendly_repr.py
datarobot_bp_workshop/magic.py
datarobot_bp_workshop/settings.py
datarobot_bp_workshop/sharing.py
datarobot_bp_workshop/task.py
datarobot_bp_workshop/user_blueprint_helper.py
datarobot_bp_workshop/utils.py
datarobot_bp_workshop/visualize.py
datarobot_bp_workshop/workshop.py
datarobot_bp_workshop/workshop_interface.py
datarobot_bp_workshop/datarobot_client/__init__.py
docs/examples/advanced/Custom.ipynb
docs/examples/advanced/FeatureSelection.ipynb
docs/examples/walkthrough/Walkthrough.ipynb