Metadata-Version: 2.1
Name: datarobot-bp-workshop
Version: 0.2.6
Summary: This client library is designed to support building DataRobot blueprints.
Home-page: https://blueprint-workshop.datarobot.com
Author: datarobot
Author-email: support@datarobot.com
Maintainer: datarobot
Maintainer-email: info@datarobot.com
License: DataRobot Tool and Utility Agreement
Platform: UNKNOWN
Classifier: Development Status :: 4 - Beta
Classifier: Intended Audience :: Developers
Classifier: Topic :: Scientific/Engineering :: Artificial Intelligence
Classifier: License :: Other/Proprietary License
Classifier: Operating System :: OS Independent
Classifier: Programming Language :: Python :: 3.7
Classifier: Programming Language :: Python :: 3.8
Classifier: Programming Language :: Python :: 3.9
Provides-Extra: dev
Provides-Extra: docs
Provides-Extra: release
Provides-Extra: lint
